chatwork/__init__.py
chatwork/admin.py
chatwork/api.py
chatwork/apps.py
chatwork/exceptions.py
chatwork/models.py
chatwork/utils.py
chatwork/views.py
chatwork/backends/__init__.py
chatwork/backends/base.py
chatwork/backends/dummy.py
chatwork/backends/http.py
chatwork/migrations/__init__.py
chatwork/templates/chatwork/_info_body.txt
chatwork/templates/chatwork/message.txt
chatwork/templates/chatwork/dummy/contacts.json
chatwork/templates/chatwork/dummy/incoming_requests.json
chatwork/templates/chatwork/dummy/me.json
chatwork/templates/chatwork/dummy/rooms.json
chatwork/templates/chatwork/dummy/rooms_POST.json
chatwork/templates/chatwork/dummy/incoming_requests/request_id.json
chatwork/templates/chatwork/dummy/my/status.json
chatwork/templates/chatwork/dummy/my/tasks.json
chatwork/templates/chatwork/dummy/rooms/room_id.json
chatwork/templates/chatwork/dummy/rooms/room_id_PUT.json
chatwork/templates/chatwork/dummy/rooms/room_id/files.json
chatwork/templates/chatwork/dummy/rooms/room_id/members.json
chatwork/templates/chatwork/dummy/rooms/room_id/members_PUT.json
chatwork/templates/chatwork/dummy/rooms/room_id/messages.json
chatwork/templates/chatwork/dummy/rooms/room_id/messages_POST.json
chatwork/templates/chatwork/dummy/rooms/room_id/tasks.json
chatwork/templates/chatwork/dummy/rooms/room_id/tasks_POST.json
chatwork/templates/chatwork/dummy/rooms/room_id/files/file_id.json
chatwork/templates/chatwork/dummy/rooms/room_id/messages/message_id.json
chatwork/templates/chatwork/dummy/rooms/room_id/messages/message_id_DELETE.json
chatwork/templates/chatwork/dummy/rooms/room_id/messages/message_id_PUT.json
chatwork/templates/chatwork/dummy/rooms/room_id/messages/read.json
chatwork/templates/chatwork/dummy/rooms/room_id/messages/unread.json
chatwork/templates/chatwork/dummy/rooms/room_id/tasks/task_id.json
django_chatwork-0.5.0.dist-info/LICENSE
django_chatwork-0.5.0.dist-info/METADATA
django_chatwork-0.5.0.dist-info/WHEEL
django_chatwork-0.5.0.dist-info/top_level.txt
django_chatwork-0.5.0.dist-info/RECORD
